example_package_vlmalo/__init__.py
example_package_vlmalo/example.py
example_package_vlmalo-0.0.2.dist-info/LICENSE
example_package_vlmalo-0.0.2.dist-info/METADATA
example_package_vlmalo-0.0.2.dist-info/WHEEL
example_package_vlmalo-0.0.2.dist-info/top_level.txt
example_package_vlmalo-0.0.2.dist-info/RECORD
