Metadata-Version: 2.1
Name: example_package_vlmalo
Version: 0.0.2
Summary: ICS0019 Python HW1
Author-email: Vladislav Malyshev <author@example.com>
Project-URL: Homepage, https://github.com/pypa/sampleproject
Project-URL: Issues, https://github.com/pypa/sampleproject/issues
Classifier: Programming Language :: Python :: 3
Classifier: License :: OSI Approved :: MIT License
Classifier: Operating System :: OS Independent
Requires-Python: >=3.8
License-File: LICENSE
